fastapi_mcp_client/__init__.py
fastapi_mcp_client/client.py
fastapi_mcp_client/config.py
fastapi_mcp_client/exceptions.py
fastapi_mcp_client/utils.py
fastapi_mcp_client-0.4.0.dist-info/METADATA
fastapi_mcp_client-0.4.0.dist-info/WHEEL
fastapi_mcp_client-0.4.0.dist-info/licenses/LICENSE
fastapi_mcp_client-0.4.0.dist-info/RECORD
