Metadata-Version: 2.4
Name: fastapi-mcp-client
Version: 0.4.0
Summary: A specialized client library for FastAPI services using Model Context Protocol (MCP) over Server-Sent Events (SSE)
Project-URL: Homepage, https://github.com/RooseveltAdvisors/fastapi-mcp-client
Project-URL: Documentation, https://github.com/RooseveltAdvisors/fastapi-mcp-client#readme
Project-URL: Issues, https://github.com/RooseveltAdvisors/fastapi-mcp-client/issues
Project-URL: Changelog, https://github.com/RooseveltAdvisors/fastapi-mcp-client/blob/main/CHANGELOG.md
Author: The FastAPI MCP Team
License: MIT License
License-File: LICENSE
Keywords: client,fastapi,mcp,model-context-protocol,server-sent-events,sse,stream
Classifier: Development Status :: 4 - Beta
Classifier: Intended Audience :: Developers
Classifier: License :: OSI Approved :: MIT License
Classifier: Programming Language :: Python :: 3
Classifier: Programming Language :: Python :: 3.10
Classifier: Programming Language :: Python :: 3.11
Classifier: Programming Language :: Python :: 3.12
Classifier: Topic :: Software Development :: Libraries :: Python Modules
Requires-Python: >=3.10
Requires-Dist: httpx>=0.24.0
Provides-Extra: dev
Requires-Dist: black>=23.0.0; extra == 'dev'
Requires-Dist: fastapi-mcp>=0.2.0; extra == 'dev'
Requires-Dist: fastapi>=0.115.12; extra == 'dev'
Requires-Dist: mypy>=1.0.0; extra == 'dev'
Requires-Dist: pytest-asyncio>=0.20.0; extra == 'dev'
Requires-Dist: pytest-cov>=4.0.0; extra == 'dev'
Requires-Dist: pytest>=7.0.0; extra == 'dev'
Requires-Dist: respx>=0.20.0; extra == 'dev'
Requires-Dist: ruff>=0.0.260; extra == 'dev'
Provides-Extra: docs
Requires-Dist: mkdocs-material>=9.0.0; extra == 'docs'
Requires-Dist: mkdocs>=1.4.0; extra == 'docs'
Requires-Dist: mkdocstrings[python]>=0.20.0; extra == 'docs'
